weatool/Aligner.py
weatool/Downloader.py
weatool/Forecast.py
weatool/Spliter.py
weatool/__init__.py
weatool-0.2.0.dist-info/licenses/LICENSE
weatool-0.2.0.dist-info/METADATA
weatool-0.2.0.dist-info/WHEEL
weatool-0.2.0.dist-info/top_level.txt
weatool-0.2.0.dist-info/RECORD
