Metadata-Version: 2.4
Name: weatool
Version: 0.2.0
Summary: framework for preprocess
Author-email: Chengrui Zhang <1447489091@qq.com>
Project-URL: Homepage, https://github.com/Neo0214
Requires-Python: >=3.13
License-File: LICENSE
Requires-Dist: numpy
Dynamic: license-file
